Metadata-Version: 2.1
Name: my-tube
Version: 1.0.0
Summary: my_tube
Home-page: UNKNOWN
Author: lucas-Dk
Author-email: lucas2000bss@gmail.com
License: MIT license
Keywords: pacotes
Platform: UNKNOWN
